pyeuromil/__init__.py
pyeuromil/euromil.py
pyeuromil/euromil_play.py
pyeuromil/euromil_utils.py
pyeuromil/data/2011.txt
pyeuromil/data/2012.txt
pyeuromil/data/2013.txt
pyeuromil/data/2014.txt
pyeuromil/data/2015.txt
pyeuromil/data/2016.txt
pyeuromil/data/2017.txt
pyeuromil/data/2018.txt
pyeuromil/data/2019.txt
pyeuromil/data/2020.txt
pyeuromil/data/2021.txt
pyeuromil-0.2.20211203.dist-info/LICENSE
pyeuromil-0.2.20211203.dist-info/METADATA
pyeuromil-0.2.20211203.dist-info/WHEEL
pyeuromil-0.2.20211203.dist-info/top_level.txt
pyeuromil-0.2.20211203.dist-info/RECORD
