Metadata-Version: 2.1
Name: pyeuromil
Version: 0.2.20211203
Summary: A python library to check and analyse Euromillions results
Home-page: https://github.com/acpirience/pyeuromil
Author: Acpirience
Author-email: acpirience@gmail.com
License: UNKNOWN
Project-URL: Documentation, https://pyeuromil.readthedocs.io
Project-URL: Code, https://github.com/acpirience/pyeuromil
Platform: any
Classifier: License :: OSI Approved :: MIT License
Classifier: Development Status :: 4 - Beta
Classifier: Programming Language :: Python :: 3.6
Classifier: Programming Language :: Python :: 3.7
Classifier: Programming Language :: Python :: 3.8
License-File: LICENSE
